organizeit/__init__.py
organizeit-0.0.1.dist-info/LICENSE.md
organizeit-0.0.1.dist-info/METADATA
organizeit-0.0.1.dist-info/WHEEL
organizeit-0.0.1.dist-info/top_level.txt
organizeit-0.0.1.dist-info/RECORD
