Metadata-Version: 2.1
Name: organizeit
Version: 0.0.1
Summary: Organizes your files in certain folders.
Home-page: https://github.com/BedantHota/python-automation
Author: Bedant Hota
Author-email: mohanesh.h2003@gmail.com
License: UNKNOWN
Platform: UNKNOWN
Classifier: Programming Language :: Python :: 3
Classifier: License :: OSI Approved :: MIT License
Classifier: Operating System :: OS Independent
Requires-Python: >=3.6
